<caaml:SnowProfile xmlns:caaml="http://caaml.org/Schemas/SnowProfileIACS/v6.0.3" xmlns:gml="http://www.opengis.net/gml" xmlns:slf="http://www.slf.ch/snowprofile/1.0" gml:id="cf593ed8-1306-411f-9d7d-15b9217b0723"><caaml:metaData><caaml:customData><slf:profiletext-list><slf:profiletext key="TEXT_BLOCK_DEFAULT"><slf:text>schneeh&#246;he am profilort total 4.40m</slf:text></slf:profiletext></slf:profiletext-list></caaml:customData></caaml:metaData><caaml:timeRef><caaml:recordTime><caaml:TimeInstant><caaml:timePosition>2001-02-12T17:30:00+01:00</caaml:timePosition></caaml:TimeInstant></caaml:recordTime><caaml:dateTimeReport>2006-11-21T12:27:18+01:00</caaml:dateTimeReport><caaml:dateTimeLastEdit>2006-11-21T12:27:18+01:00</caaml:dateTimeLastEdit></caaml:timeRef><caaml:srcRef/><caaml:locRef><caaml:name>H&#246;henprofil val strem, sedrun, GR</caaml:name><caaml:validElevation><caaml:ElevationPosition uom="m"><caaml:position>2600</caaml:position></caaml:ElevationPosition></caaml:validElevation><caaml:validAspect><caaml:AspectPosition><caaml:position>W</caaml:position></caaml:AspectPosition></caaml:validAspect><caaml:validSlopeAngle><caaml:SlopeAnglePosition uom="deg"><caaml:position>32</caaml:position></caaml:SlopeAnglePosition></caaml:validSlopeAngle><caaml:pointLocation><gml:Point id="pointID" srsName="urn:ogc:def:crs:OGC:1.3:CRS84" srsDimension="2"><gml:pos>8.774312 46.726483</gml:pos></gml:Point></caaml:pointLocation></caaml:locRef><caaml:snowProfileResultsOf><caaml:SnowProfileMeasurements dir="top down"><caaml:profileDepth uom="cm">200.0</caaml:profileDepth><caaml:weatherCond><caaml:airTempPres uom="degC">-1.0</caaml:airTempPres></caaml:weatherCond><caaml:snowPackCond><caaml:hS><caaml:Components><caaml:height uom="cm">200.0</caaml:height></caaml:Components></caaml:hS></caaml:snowPackCond><caaml:stratProfile><caaml:Layer><caaml:depthTop uom="cm">0.0</caaml:depthTop><caaml:thickness uom="cm">28.0</caaml:thickness><caaml:wetness uom="">D</caaml:wetness><caaml:grainFormPrimary>DF</caaml:grainFormPrimary><caaml:grainSize uom="mm"><caaml:Components><caaml:avg>0.5</caaml:avg></caaml:Components></caaml:grainSize><caaml:hardness uom="">F</caaml:hardness></caaml:Layer><caaml:Layer><caaml:depthTop uom="cm">28.0</caaml:depthTop><caaml:thickness uom="cm">72.0</caaml:thickness><caaml:wetness uom="">D</caaml:wetness><caaml:grainFormPrimary>DF</caaml:grainFormPrimary><caaml:grainSize uom="mm"><caaml:Components><caaml:avg>0.5</caaml:avg></caaml:Components></caaml:grainSize><caaml:hardness uom="">1F</caaml:hardness></caaml:Layer><caaml:Layer><caaml:depthTop uom="cm">100.0</caaml:depthTop><caaml:thickness uom="cm">30.0</caaml:thickness><caaml:wetness uom="">D</caaml:wetness><caaml:grainFormPrimary>DF</caaml:grainFormPrimary><caaml:grainFormSecondary>RG</caaml:grainFormSecondary><caaml:grainSize uom="mm"><caaml:Components><caaml:avg>0.5</caaml:avg></caaml:Components></caaml:grainSize><caaml:hardness uom="">1F-P</caaml:hardness></caaml:Layer><caaml:Layer><caaml:depthTop uom="cm">130.0</caaml:depthTop><caaml:thickness uom="cm">45.0</caaml:thickness><caaml:wetness uom="">D</caaml:wetness><caaml:grainFormPrimary>RG</caaml:grainFormPrimary><caaml:grainSize uom="mm"><caaml:Components><caaml:avg>0.5</caaml:avg></caaml:Components></caaml:grainSize><caaml:hardness uom="">P</caaml:hardness></caaml:Layer><caaml:Layer><caaml:depthTop uom="cm">175.0</caaml:depthTop><caaml:thickness uom="cm">25.0</caaml:thickness><caaml:wetness uom="">D</caaml:wetness><caaml:grainFormPrimary>RG</caaml:grainFormPrimary><caaml:grainFormSecondary>FC</caaml:grainFormSecondary><caaml:grainSize uom="mm"><caaml:Components><caaml:avg>0.5</caaml:avg><caaml:avgMax>1.0</caaml:avgMax></caaml:Components></caaml:grainSize><caaml:hardness uom="">1F-P</caaml:hardness></caaml:Layer></caaml:stratProfile><caaml:tempProfile><caaml:Obs><caaml:depth uom="cm">0.0</caaml:depth><caaml:snowTemp uom="degC">-1.0</caaml:snowTemp></caaml:Obs><caaml:Obs><caaml:depth uom="cm">25.0</caaml:depth><caaml:snowTemp uom="degC">-4.0</caaml:snowTemp></caaml:Obs><caaml:Obs><caaml:depth uom="cm">30.0</caaml:depth><caaml:snowTemp uom="degC">-4.0</caaml:snowTemp></caaml:Obs><caaml:Obs><caaml:depth uom="cm">95.0</caaml:depth><caaml:snowTemp uom="degC">-5.0</caaml:snowTemp></caaml:Obs><caaml:Obs><caaml:depth uom="cm">105.0</caaml:depth><caaml:snowTemp uom="degC">-5.0</caaml:snowTemp></caaml:Obs><caaml:Obs><caaml:depth uom="cm">125.0</caaml:depth><caaml:snowTemp uom="degC">-5.0</caaml:snowTemp></caaml:Obs><caaml:Obs><caaml:depth uom="cm">135.0</caaml:depth><caaml:snowTemp uom="degC">-5.0</caaml:snowTemp></caaml:Obs><caaml:Obs><caaml:depth uom="cm">170.0</caaml:depth><caaml:snowTemp uom="degC">-5.0</caaml:snowTemp></caaml:Obs><caaml:Obs><caaml:depth uom="cm">180.0</caaml:depth><caaml:snowTemp uom="degC">-5.0</caaml:snowTemp></caaml:Obs><caaml:Obs><caaml:depth uom="cm">200.0</caaml:depth><caaml:snowTemp uom="degC">-5.0</caaml:snowTemp></caaml:Obs></caaml:tempProfile><caaml:hardnessProfile uomWeightHammer="kg" uomWeightTube="kg" uomDropHeight="cm"><caaml:hardnessMetaData><caaml:methodOfMeas>Ram Sonde</caaml:methodOfMeas></caaml:hardnessMetaData><caaml:Layer><caaml:depthTop uom="cm">0.0</caaml:depthTop><caaml:thickness uom="cm">28.0</caaml:thickness><caaml:hardness uom="N">9.81</caaml:hardness><caaml:weightHammer>0.0</caaml:weightHammer><caaml:weightTube>1.0</caaml:weightTube><caaml:nDrops>0.0</caaml:nDrops><caaml:dropHeight>0.0</caaml:dropHeight></caaml:Layer><caaml:Layer><caaml:depthTop uom="cm">28.0</caaml:depthTop><caaml:thickness uom="cm">6.0</caaml:thickness><caaml:hardness uom="N">19.62</caaml:hardness><caaml:weightHammer>1.0</caaml:weightHammer><caaml:weightTube>1.0</caaml:weightTube><caaml:nDrops>0.0</caaml:nDrops><caaml:dropHeight>0.0</caaml:dropHeight></caaml:Layer><caaml:Layer><caaml:depthTop uom="cm">34.0</caaml:depthTop><caaml:thickness uom="cm">4.0</caaml:thickness><caaml:hardness uom="N">117.72</caaml:hardness><caaml:weightHammer>1.0</caaml:weightHammer><caaml:weightTube>1.0</caaml:weightTube><caaml:nDrops>4.0</caaml:nDrops><caaml:dropHeight>10.0</caaml:dropHeight></caaml:Layer><caaml:Layer><caaml:depthTop uom="cm">38.0</caaml:depthTop><caaml:thickness uom="cm">2.0</caaml:thickness><caaml:hardness uom="N">240.345</caaml:hardness><caaml:weightHammer>1.0</caaml:weightHammer><caaml:weightTube>1.0</caaml:weightTube><caaml:nDrops>3.0</caaml:nDrops><caaml:dropHeight>15.0</caaml:dropHeight></caaml:Layer><caaml:Layer><caaml:depthTop uom="cm">40.0</caaml:depthTop><caaml:thickness uom="cm">5.0</caaml:thickness><caaml:hardness uom="N">107.91000000000001</caaml:hardness><caaml:weightHammer>1.0</caaml:weightHammer><caaml:weightTube>1.0</caaml:weightTube><caaml:nDrops>3.0</caaml:nDrops><caaml:dropHeight>15.0</caaml:dropHeight></caaml:Layer><caaml:Layer><caaml:depthTop uom="cm">45.0</caaml:depthTop><caaml:thickness uom="cm">5.0</caaml:thickness><caaml:hardness uom="N">137.34</caaml:hardness><caaml:weightHammer>1.0</caaml:weightHammer><caaml:weightTube>1.0</caaml:weightTube><caaml:nDrops>4.0</caaml:nDrops><caaml:dropHeight>15.0</caaml:dropHeight></caaml:Layer><caaml:Layer><caaml:depthTop uom="cm">50.0</caaml:depthTop><caaml:thickness uom="cm">5.0</caaml:thickness><caaml:hardness uom="N">107.91000000000001</caaml:hardness><caaml:weightHammer>1.0</caaml:weightHammer><caaml:weightTube>1.0</caaml:weightTube><caaml:nDrops>3.0</caaml:nDrops><caaml:dropHeight>15.0</caaml:dropHeight></caaml:Layer><caaml:Layer><caaml:depthTop uom="cm">55.0</caaml:depthTop><caaml:thickness uom="cm">4.0</caaml:thickness><caaml:hardness uom="N">129.98250000000002</caaml:hardness><caaml:weightHammer>1.0</caaml:weightHammer><caaml:weightTube>1.0</caaml:weightTube><caaml:nDrops>3.0</caaml:nDrops><caaml:dropHeight>15.0</caaml:dropHeight></caaml:Layer><caaml:Layer><caaml:depthTop uom="cm">59.0</caaml:depthTop><caaml:thickness uom="cm">6.0</caaml:thickness><caaml:hardness uom="N">117.72</caaml:hardness><caaml:weightHammer>1.0</caaml:weightHammer><caaml:weightTube>1.0</caaml:weightTube><caaml:nDrops>4.0</caaml:nDrops><caaml:dropHeight>15.0</caaml:dropHeight></caaml:Layer><caaml:Layer><caaml:depthTop uom="cm">65.0</caaml:depthTop><caaml:thickness uom="cm">5.0</caaml:thickness><caaml:hardness uom="N">78.48</caaml:hardness><caaml:weightHammer>1.0</caaml:weightHammer><caaml:weightTube>1.0</caaml:weightTube><caaml:nDrops>2.0</caaml:nDrops><caaml:dropHeight>15.0</caaml:dropHeight></caaml:Layer><caaml:Layer><caaml:depthTop uom="cm">70.0</caaml:depthTop><caaml:thickness uom="cm">4.0</caaml:thickness><caaml:hardness uom="N">93.19500000000001</caaml:hardness><caaml:weightHammer>1.0</caaml:weightHammer><caaml:weightTube>1.0</caaml:weightTube><caaml:nDrops>2.0</caaml:nDrops><caaml:dropHeight>15.0</caaml:dropHeight></caaml:Layer><caaml:Layer><caaml:depthTop uom="cm">74.0</caaml:depthTop><caaml:thickness uom="cm">4.0</caaml:thickness><caaml:hardness uom="N">93.19500000000001</caaml:hardness><caaml:weightHammer>1.0</caaml:weightHammer><caaml:weightTube>1.0</caaml:weightTube><caaml:nDrops>3.0</caaml:nDrops><caaml:dropHeight>10.0</caaml:dropHeight></caaml:Layer><caaml:Layer><caaml:depthTop uom="cm">78.0</caaml:depthTop><caaml:thickness uom="cm">4.0</caaml:thickness><caaml:hardness uom="N">93.19500000000001</caaml:hardness><caaml:weightHammer>1.0</caaml:weightHammer><caaml:weightTube>1.0</caaml:weightTube><caaml:nDrops>3.0</caaml:nDrops><caaml:dropHeight>10.0</caaml:dropHeight></caaml:Layer><caaml:Layer><caaml:depthTop uom="cm">82.0</caaml:depthTop><caaml:thickness uom="cm">5.0</caaml:thickness><caaml:hardness uom="N">78.48</caaml:hardness><caaml:weightHammer>1.0</caaml:weightHammer><caaml:weightTube>1.0</caaml:weightTube><caaml:nDrops>3.0</caaml:nDrops><caaml:dropHeight>10.0</caaml:dropHeight></caaml:Layer><caaml:Layer><caaml:depthTop uom="cm">87.0</caaml:depthTop><caaml:thickness uom="cm">4.0</caaml:thickness><caaml:hardness uom="N">93.19500000000001</caaml:hardness><caaml:weightHammer>1.0</caaml:weightHammer><caaml:weightTube>1.0</caaml:weightTube><caaml:nDrops>3.0</caaml:nDrops><caaml:dropHeight>10.0</caaml:dropHeight></caaml:Layer><caaml:Layer><caaml:depthTop uom="cm">91.0</caaml:depthTop><caaml:thickness uom="cm">4.0</caaml:thickness><caaml:hardness uom="N">117.72</caaml:hardness><caaml:weightHammer>1.0</caaml:weightHammer><caaml:weightTube>1.0</caaml:weightTube><caaml:nDrops>4.0</caaml:nDrops><caaml:dropHeight>10.0</caaml:dropHeight></caaml:Layer><caaml:Layer><caaml:depthTop uom="cm">95.0</caaml:depthTop><caaml:thickness uom="cm">5.0</caaml:thickness><caaml:hardness uom="N">196.20000000000002</caaml:hardness><caaml:weightHammer>1.0</caaml:weightHammer><caaml:weightTube>1.0</caaml:weightTube><caaml:nDrops>9.0</caaml:nDrops><caaml:dropHeight>10.0</caaml:dropHeight></caaml:Layer><caaml:Layer><caaml:depthTop uom="cm">100.0</caaml:depthTop><caaml:thickness uom="cm">6.0</caaml:thickness><caaml:hardness uom="N">117.72</caaml:hardness><caaml:weightHammer>1.0</caaml:weightHammer><caaml:weightTube>1.0</caaml:weightTube><caaml:nDrops>3.0</caaml:nDrops><caaml:dropHeight>20.0</caaml:dropHeight></caaml:Layer><caaml:Layer><caaml:depthTop uom="cm">106.0</caaml:depthTop><caaml:thickness uom="cm">4.0</caaml:thickness><caaml:hardness uom="N">166.77</caaml:hardness><caaml:weightHammer>1.0</caaml:weightHammer><caaml:weightTube>1.0</caaml:weightTube><caaml:nDrops>3.0</caaml:nDrops><caaml:dropHeight>20.0</caaml:dropHeight></caaml:Layer><caaml:Layer><caaml:depthTop uom="cm">110.0</caaml:depthTop><caaml:thickness uom="cm">6.0</caaml:thickness><caaml:hardness uom="N">215.82000000000002</caaml:hardness><caaml:weightHammer>1.0</caaml:weightHammer><caaml:weightTube>1.0</caaml:weightTube><caaml:nDrops>4.0</caaml:nDrops><caaml:dropHeight>30.0</caaml:dropHeight></caaml:Layer><caaml:Layer><caaml:depthTop uom="cm">116.0</caaml:depthTop><caaml:thickness uom="cm">5.0</caaml:thickness><caaml:hardness uom="N">196.20000000000002</caaml:hardness><caaml:weightHammer>1.0</caaml:weightHammer><caaml:weightTube>1.0</caaml:weightTube><caaml:nDrops>3.0</caaml:nDrops><caaml:dropHeight>30.0</caaml:dropHeight></caaml:Layer><caaml:Layer><caaml:depthTop uom="cm">121.0</caaml:depthTop><caaml:thickness uom="cm">4.0</caaml:thickness><caaml:hardness uom="N">313.92</caaml:hardness><caaml:weightHammer>1.0</caaml:weightHammer><caaml:weightTube>1.0</caaml:weightTube><caaml:nDrops>4.0</caaml:nDrops><caaml:dropHeight>30.0</caaml:dropHeight></caaml:Layer><caaml:Layer><caaml:depthTop uom="cm">125.0</caaml:depthTop><caaml:thickness uom="cm">4.0</caaml:thickness><caaml:hardness uom="N">215.82000000000002</caaml:hardness><caaml:weightHammer>1.0</caaml:weightHammer><caaml:weightTube>1.0</caaml:weightTube><caaml:nDrops>2.0</caaml:nDrops><caaml:dropHeight>40.0</caaml:dropHeight></caaml:Layer><caaml:Layer><caaml:depthTop uom="cm">129.0</caaml:depthTop><caaml:thickness uom="cm">6.0</caaml:thickness><caaml:hardness uom="N">215.82000000000002</caaml:hardness><caaml:weightHammer>1.0</caaml:weightHammer><caaml:weightTube>1.0</caaml:weightTube><caaml:nDrops>3.0</caaml:nDrops><caaml:dropHeight>40.0</caaml:dropHeight></caaml:Layer><caaml:Layer><caaml:depthTop uom="cm">135.0</caaml:depthTop><caaml:thickness uom="cm">4.0</caaml:thickness><caaml:hardness uom="N">412.02000000000004</caaml:hardness><caaml:weightHammer>1.0</caaml:weightHammer><caaml:weightTube>1.0</caaml:weightTube><caaml:nDrops>4.0</caaml:nDrops><caaml:dropHeight>40.0</caaml:dropHeight></caaml:Layer><caaml:Layer><caaml:depthTop uom="cm">139.0</caaml:depthTop><caaml:thickness uom="cm">3.0</caaml:thickness><caaml:hardness uom="N">510.12</caaml:hardness><caaml:weightHammer>1.0</caaml:weightHammer><caaml:weightTube>1.0</caaml:weightTube><caaml:nDrops>3.0</caaml:nDrops><caaml:dropHeight>50.0</caaml:dropHeight></caaml:Layer><caaml:Layer><caaml:depthTop uom="cm">142.0</caaml:depthTop><caaml:thickness uom="cm">7.0</caaml:thickness><caaml:hardness uom="N">229.8342857142857</caaml:hardness><caaml:weightHammer>1.0</caaml:weightHammer><caaml:weightTube>1.0</caaml:weightTube><caaml:nDrops>3.0</caaml:nDrops><caaml:dropHeight>50.0</caaml:dropHeight></caaml:Layer><caaml:Layer><caaml:depthTop uom="cm">149.0</caaml:depthTop><caaml:thickness uom="cm">6.0</caaml:thickness><caaml:hardness uom="N">346.62000000000006</caaml:hardness><caaml:weightHammer>1.0</caaml:weightHammer><caaml:weightTube>1.0</caaml:weightTube><caaml:nDrops>4.0</caaml:nDrops><caaml:dropHeight>50.0</caaml:dropHeight></caaml:Layer><caaml:Layer><caaml:depthTop uom="cm">155.0</caaml:depthTop><caaml:thickness uom="cm">5.0</caaml:thickness><caaml:hardness uom="N">412.02000000000004</caaml:hardness><caaml:weightHammer>1.0</caaml:weightHammer><caaml:weightTube>1.0</caaml:weightTube><caaml:nDrops>4.0</caaml:nDrops><caaml:dropHeight>50.0</caaml:dropHeight></caaml:Layer><caaml:Layer><caaml:depthTop uom="cm">160.0</caaml:depthTop><caaml:thickness uom="cm">7.0</caaml:thickness><caaml:hardness uom="N">299.90571428571434</caaml:hardness><caaml:weightHammer>1.0</caaml:weightHammer><caaml:weightTube>1.0</caaml:weightTube><caaml:nDrops>4.0</caaml:nDrops><caaml:dropHeight>50.0</caaml:dropHeight></caaml:Layer><caaml:Layer><caaml:depthTop uom="cm">167.0</caaml:depthTop><caaml:thickness uom="cm">10.0</caaml:thickness><caaml:hardness uom="N">264.87</caaml:hardness><caaml:weightHammer>1.0</caaml:weightHammer><caaml:weightTube>1.0</caaml:weightTube><caaml:nDrops>5.0</caaml:nDrops><caaml:dropHeight>50.0</caaml:dropHeight></caaml:Layer><caaml:Layer><caaml:depthTop uom="cm">177.0</caaml:depthTop><caaml:thickness uom="cm">8.0</caaml:thickness><caaml:hardness uom="N">203.5575</caaml:hardness><caaml:weightHammer>1.0</caaml:weightHammer><caaml:weightTube>1.0</caaml:weightTube><caaml:nDrops>3.0</caaml:nDrops><caaml:dropHeight>50.0</caaml:dropHeight></caaml:Layer><caaml:Layer><caaml:depthTop uom="cm">185.0</caaml:depthTop><caaml:thickness uom="cm">5.0</caaml:thickness><caaml:hardness uom="N">255.06</caaml:hardness><caaml:weightHammer>1.0</caaml:weightHammer><caaml:weightTube>1.0</caaml:weightTube><caaml:nDrops>3.0</caaml:nDrops><caaml:dropHeight>40.0</caaml:dropHeight></caaml:Layer><caaml:Layer><caaml:depthTop uom="cm">190.0</caaml:depthTop><caaml:thickness uom="cm">3.0</caaml:thickness><caaml:hardness uom="N">412.02000000000004</caaml:hardness><caaml:weightHammer>1.0</caaml:weightHammer><caaml:weightTube>1.0</caaml:weightTube><caaml:nDrops>3.0</caaml:nDrops><caaml:dropHeight>40.0</caaml:dropHeight></caaml:Layer><caaml:Layer><caaml:depthTop uom="cm">193.0</caaml:depthTop><caaml:thickness uom="cm">7.0</caaml:thickness><caaml:hardness uom="N">299.90571428571434</caaml:hardness><caaml:weightHammer>1.0</caaml:weightHammer><caaml:weightTube>1.0</caaml:weightTube><caaml:nDrops>5.0</caaml:nDrops><caaml:dropHeight>40.0</caaml:dropHeight></caaml:Layer></caaml:hardnessProfile><caaml:stbTests><caaml:RBlockTest><caaml:failedOn><caaml:Layer><caaml:depthTop uom="cm">28.0</caaml:depthTop></caaml:Layer><caaml:Results><caaml:testScore>RB3</caaml:testScore></caaml:Results></caaml:failedOn></caaml:RBlockTest></caaml:stbTests></caaml:SnowProfileMeasurements></caaml:snowProfileResultsOf></caaml:SnowProfile>