<caaml:SnowProfile xmlns:caaml="http://caaml.org/Schemas/SnowProfileIACS/v6.0.3" xmlns:gml="http://www.opengis.net/gml" xmlns:slf="http://www.slf.ch/snowprofile/1.0" gml:id="e649c89f-fb59-4b7e-9291-90831f18464f"><caaml:timeRef><caaml:recordTime><caaml:TimeInstant><caaml:timePosition>2005-03-12T12:30:00+01:00</caaml:timePosition></caaml:TimeInstant></caaml:recordTime><caaml:dateTimeReport>2006-11-21T18:10:39+01:00</caaml:dateTimeReport><caaml:dateTimeLastEdit>2006-11-21T18:10:39+01:00</caaml:dateTimeLastEdit></caaml:timeRef><caaml:srcRef/><caaml:locRef><caaml:name>Piz da las Coluonnas - Julierpass, St. Moritz</caaml:name><caaml:validElevation><caaml:ElevationPosition uom="m"><caaml:position>2340</caaml:position></caaml:ElevationPosition></caaml:validElevation><caaml:validAspect><caaml:AspectPosition><caaml:position>NW</caaml:position></caaml:AspectPosition></caaml:validAspect><caaml:validSlopeAngle><caaml:SlopeAnglePosition uom="deg"><caaml:position>39</caaml:position></caaml:SlopeAnglePosition></caaml:validSlopeAngle><caaml:pointLocation><gml:Point id="pointID" srsName="urn:ogc:def:crs:OGC:1.3:CRS84" srsDimension="2"><gml:pos>9.723777 46.467527</gml:pos></gml:Point></caaml:pointLocation></caaml:locRef><caaml:snowProfileResultsOf><caaml:SnowProfileMeasurements dir="top down"><caaml:profileDepth uom="cm">140.5</caaml:profileDepth><caaml:weatherCond><caaml:airTempPres uom="degC">-6.5</caaml:airTempPres></caaml:weatherCond><caaml:snowPackCond><caaml:hS><caaml:Components><caaml:height uom="cm">140.5</caaml:height></caaml:Components></caaml:hS></caaml:snowPackCond><caaml:stratProfile><caaml:Layer><caaml:depthTop uom="cm">0.0</caaml:depthTop><caaml:thickness uom="cm">0.5</caaml:thickness><caaml:wetness uom="">D</caaml:wetness><caaml:grainFormPrimary>SH</caaml:grainFormPrimary><caaml:grainSize uom="mm"><caaml:Components><caaml:avg>0.5</caaml:avg><caaml:avgMax>1.5</caaml:avgMax></caaml:Components></caaml:grainSize><caaml:hardness uom="">F</caaml:hardness></caaml:Layer><caaml:Layer><caaml:depthTop uom="cm">0.5</caaml:depthTop><caaml:thickness uom="cm">25.0</caaml:thickness><caaml:wetness uom="">D</caaml:wetness><caaml:grainFormPrimary>PP</caaml:grainFormPrimary><caaml:grainFormSecondary>DF</caaml:grainFormSecondary><caaml:grainSize uom="mm"><caaml:Components><caaml:avg>0.25</caaml:avg><caaml:avgMax>1.0</caaml:avgMax></caaml:Components></caaml:grainSize><caaml:hardness uom="">F</caaml:hardness></caaml:Layer><caaml:Layer><caaml:depthTop uom="cm">25.5</caaml:depthTop><caaml:thickness uom="cm">1.0</caaml:thickness><caaml:wetness uom="">D</caaml:wetness><caaml:grainFormPrimary>SH</caaml:grainFormPrimary><caaml:grainSize uom="mm"><caaml:Components><caaml:avg>0.5</caaml:avg><caaml:avgMax>3.0</caaml:avgMax></caaml:Components></caaml:grainSize><caaml:hardness uom="">F</caaml:hardness></caaml:Layer><caaml:Layer><caaml:depthTop uom="cm">26.5</caaml:depthTop><caaml:thickness uom="cm">15.0</caaml:thickness><caaml:wetness uom="">D</caaml:wetness><caaml:grainFormPrimary>FC</caaml:grainFormPrimary><caaml:grainSize uom="mm"><caaml:Components><caaml:avg>0.5</caaml:avg><caaml:avgMax>1.0</caaml:avgMax></caaml:Components></caaml:grainSize><caaml:hardness uom="">F-4F</caaml:hardness></caaml:Layer><caaml:Layer><caaml:depthTop uom="cm">41.5</caaml:depthTop><caaml:thickness uom="cm">3.0</caaml:thickness><caaml:wetness uom="">D</caaml:wetness><caaml:grainFormPrimary>FC</caaml:grainFormPrimary><caaml:grainSize uom="mm"><caaml:Components><caaml:avg>0.5</caaml:avg><caaml:avgMax>1.0</caaml:avgMax></caaml:Components></caaml:grainSize><caaml:hardness uom="">1F-P</caaml:hardness></caaml:Layer><caaml:Layer><caaml:depthTop uom="cm">44.5</caaml:depthTop><caaml:thickness uom="cm">22.0</caaml:thickness><caaml:wetness uom="">D</caaml:wetness><caaml:grainFormPrimary>FC</caaml:grainFormPrimary><caaml:grainFormSecondary>DH</caaml:grainFormSecondary><caaml:grainSize uom="mm"><caaml:Components><caaml:avg>0.5</caaml:avg><caaml:avgMax>1.5</caaml:avgMax></caaml:Components></caaml:grainSize><caaml:hardness uom="">4F</caaml:hardness></caaml:Layer><caaml:Layer><caaml:depthTop uom="cm">66.5</caaml:depthTop><caaml:thickness uom="cm">1.0</caaml:thickness><caaml:wetness uom="">D</caaml:wetness><caaml:grainFormPrimary>FC</caaml:grainFormPrimary><caaml:grainSize uom="mm"><caaml:Components><caaml:avg>0.25</caaml:avg><caaml:avgMax>1.0</caaml:avgMax></caaml:Components></caaml:grainSize><caaml:hardness uom="">P</caaml:hardness></caaml:Layer><caaml:Layer><caaml:depthTop uom="cm">67.5</caaml:depthTop><caaml:thickness uom="cm">23.0</caaml:thickness><caaml:wetness uom="">D</caaml:wetness><caaml:grainFormPrimary>FC</caaml:grainFormPrimary><caaml:grainFormSecondary>DH</caaml:grainFormSecondary><caaml:grainSize uom="mm"><caaml:Components><caaml:avg>0.5</caaml:avg><caaml:avgMax>2.0</caaml:avgMax></caaml:Components></caaml:grainSize><caaml:hardness uom="">4F-1F</caaml:hardness></caaml:Layer><caaml:Layer><caaml:depthTop uom="cm">90.5</caaml:depthTop><caaml:thickness uom="cm">50.0</caaml:thickness><caaml:wetness uom="">D</caaml:wetness><caaml:grainFormPrimary>DH</caaml:grainFormPrimary><caaml:grainSize uom="mm"><caaml:Components><caaml:avg>1.0</caaml:avg><caaml:avgMax>5.0</caaml:avgMax></caaml:Components></caaml:grainSize><caaml:hardness uom="">F-4F</caaml:hardness></caaml:Layer></caaml:stratProfile><caaml:tempProfile><caaml:Obs><caaml:depth uom="cm">0.0</caaml:depth><caaml:snowTemp uom="degC">-9.8</caaml:snowTemp></caaml:Obs><caaml:Obs><caaml:depth uom="cm">0.5</caaml:depth><caaml:snowTemp uom="degC">-9.8</caaml:snowTemp></caaml:Obs><caaml:Obs><caaml:depth uom="cm">10.5</caaml:depth><caaml:snowTemp uom="degC">-9.2</caaml:snowTemp></caaml:Obs><caaml:Obs><caaml:depth uom="cm">20.5</caaml:depth><caaml:snowTemp uom="degC">-8.5</caaml:snowTemp></caaml:Obs><caaml:Obs><caaml:depth uom="cm">30.5</caaml:depth><caaml:snowTemp uom="degC">-7.3</caaml:snowTemp></caaml:Obs><caaml:Obs><caaml:depth uom="cm">40.5</caaml:depth><caaml:snowTemp uom="degC">-6.7</caaml:snowTemp></caaml:Obs><caaml:Obs><caaml:depth uom="cm">60.5</caaml:depth><caaml:snowTemp uom="degC">-6.0</caaml:snowTemp></caaml:Obs><caaml:Obs><caaml:depth uom="cm">80.5</caaml:depth><caaml:snowTemp uom="degC">-5.1</caaml:snowTemp></caaml:Obs><caaml:Obs><caaml:depth uom="cm">100.5</caaml:depth><caaml:snowTemp uom="degC">-4.3</caaml:snowTemp></caaml:Obs><caaml:Obs><caaml:depth uom="cm">140.5</caaml:depth><caaml:snowTemp uom="degC">-2.6</caaml:snowTemp></caaml:Obs></caaml:tempProfile><caaml:hardnessProfile uomWeightHammer="kg" uomWeightTube="kg" uomDropHeight="cm"><caaml:hardnessMetaData><caaml:methodOfMeas>Ram Sonde</caaml:methodOfMeas></caaml:hardnessMetaData><caaml:Layer><caaml:depthTop uom="cm">0.0</caaml:depthTop><caaml:thickness uom="cm">40.0</caaml:thickness><caaml:hardness uom="N">9.81</caaml:hardness><caaml:weightHammer>0.0</caaml:weightHammer><caaml:weightTube>1.0</caaml:weightTube><caaml:nDrops>0.0</caaml:nDrops><caaml:dropHeight>0.0</caaml:dropHeight></caaml:Layer><caaml:Layer><caaml:depthTop uom="cm">40.0</caaml:depthTop><caaml:thickness uom="cm">0.0</caaml:thickness><caaml:hardness uom="N">19.62</caaml:hardness><caaml:weightHammer>1.0</caaml:weightHammer><caaml:weightTube>1.0</caaml:weightTube><caaml:nDrops>0.0</caaml:nDrops><caaml:dropHeight>0.0</caaml:dropHeight></caaml:Layer><caaml:Layer><caaml:depthTop uom="cm">40.0</caaml:depthTop><caaml:thickness uom="cm">49.0</caaml:thickness><caaml:hardness uom="N">20.621020408163265</caaml:hardness><caaml:weightHammer>1.0</caaml:weightHammer><caaml:weightTube>1.0</caaml:weightTube><caaml:nDrops>1.0</caaml:nDrops><caaml:dropHeight>5.0</caaml:dropHeight></caaml:Layer><caaml:Layer><caaml:depthTop uom="cm">89.0</caaml:depthTop><caaml:thickness uom="cm">46.0</caaml:thickness><caaml:hardness uom="N">30.49630434782609</caaml:hardness><caaml:weightHammer>1.0</caaml:weightHammer><caaml:weightTube>2.0</caaml:weightTube><caaml:nDrops>1.0</caaml:nDrops><caaml:dropHeight>5.0</caaml:dropHeight></caaml:Layer><caaml:Layer><caaml:depthTop uom="cm">135.0</caaml:depthTop><caaml:thickness uom="cm">5.0</caaml:thickness><caaml:hardness uom="N">78.48</caaml:hardness><caaml:weightHammer>1.0</caaml:weightHammer><caaml:weightTube>2.0</caaml:weightTube><caaml:nDrops>5.0</caaml:nDrops><caaml:dropHeight>5.0</caaml:dropHeight></caaml:Layer></caaml:hardnessProfile><caaml:stbTests><caaml:RBlockTest><caaml:failedOn><caaml:Layer><caaml:depthTop uom="cm">26.5</caaml:depthTop></caaml:Layer><caaml:Results><caaml:testScore>RB1</caaml:testScore><caaml:fractureCharacter>Clean</caaml:fractureCharacter><caaml:releaseType>WB</caaml:releaseType></caaml:Results></caaml:failedOn><caaml:failedOn><caaml:Layer><caaml:depthTop uom="cm">44.5</caaml:depthTop></caaml:Layer><caaml:Results><caaml:testScore>RB3</caaml:testScore><caaml:fractureCharacter>Clean</caaml:fractureCharacter><caaml:releaseType>MB</caaml:releaseType></caaml:Results></caaml:failedOn><caaml:failedOn><caaml:Layer><caaml:depthTop uom="cm">90.5</caaml:depthTop></caaml:Layer><caaml:Results><caaml:testScore>RB5</caaml:testScore><caaml:fractureCharacter>Irregular</caaml:fractureCharacter><caaml:releaseType>MB</caaml:releaseType></caaml:Results></caaml:failedOn></caaml:RBlockTest><caaml:ComprTest><caaml:failedOn><caaml:Layer><caaml:depthTop uom="cm">26.5</caaml:depthTop></caaml:Layer><caaml:Results><caaml:testScore>3</caaml:testScore></caaml:Results></caaml:failedOn><caaml:failedOn><caaml:Layer><caaml:depthTop uom="cm">44.5</caaml:depthTop></caaml:Layer><caaml:Results><caaml:testScore>16</caaml:testScore></caaml:Results></caaml:failedOn><caaml:failedOn><caaml:Layer><caaml:depthTop uom="cm">90.5</caaml:depthTop></caaml:Layer><caaml:Results><caaml:testScore>25</caaml:testScore></caaml:Results></caaml:failedOn></caaml:ComprTest></caaml:stbTests></caaml:SnowProfileMeasurements></caaml:snowProfileResultsOf></caaml:SnowProfile>