<caaml:SnowProfile xmlns:caaml="http://caaml.org/Schemas/SnowProfileIACS/v6.0.3" xmlns:gml="http://www.opengis.net/gml" xmlns:slf="http://www.slf.ch/snowprofile/1.0" gml:id="388dcb81-65df-4a52-b2ed-05a2bb7374f9"><caaml:metaData><caaml:customData><slf:profiletext-list><slf:profiletext key="TEXT_BLOCK_DEFAULT"><slf:text>PROFILE LOCATION
----------------
IMIS_Messstation, FLU2

PROFILE
-------
Flachfeldprofil

SNOW SURFACE
------------
Windbeeinflusst

SNOW DRIFT
----------
Frische TSA

ALARM SIGNS
-----------
Kleines Wumm

COMMENT
-------
HS: median = 92 cm, max = 240 cm, min = 28 cm</slf:text></slf:profiletext></slf:profiletext-list></caaml:customData></caaml:metaData><caaml:timeRef><caaml:recordTime><caaml:TimeInstant><caaml:timePosition>2017-03-03T13:50:00+01:00</caaml:timePosition></caaml:TimeInstant></caaml:recordTime><caaml:dateTimeReport>2017-03-03T17:15:59+01:00</caaml:dateTimeReport><caaml:dateTimeLastEdit>2017-03-03T17:44:12+01:00</caaml:dateTimeLastEdit></caaml:timeRef><caaml:srcRef/><caaml:locRef><caaml:name>Zernez, Fl&#252;elapass</caaml:name><caaml:validElevation><caaml:ElevationPosition uom="m"><caaml:position>2390</caaml:position></caaml:ElevationPosition></caaml:validElevation><caaml:validSlopeAngle><caaml:SlopeAnglePosition uom="deg"><caaml:position>0</caaml:position></caaml:SlopeAnglePosition></caaml:validSlopeAngle><caaml:pointLocation><gml:Point id="pointID" srsName="urn:ogc:def:crs:OGC:1.3:CRS84" srsDimension="2"><gml:pos>9.94642 46.752748</gml:pos></gml:Point></caaml:pointLocation></caaml:locRef><caaml:snowProfileResultsOf><caaml:SnowProfileMeasurements dir="top down"><caaml:profileDepth uom="cm">76.0</caaml:profileDepth><caaml:weatherCond><caaml:airTempPres uom="degC">-1.4</caaml:airTempPres></caaml:weatherCond><caaml:snowPackCond><caaml:hS><caaml:Components><caaml:height uom="cm">76.0</caaml:height></caaml:Components></caaml:hS></caaml:snowPackCond><caaml:stratProfile><caaml:Layer><caaml:depthTop uom="cm">0.0</caaml:depthTop><caaml:thickness uom="cm">3.0</caaml:thickness><caaml:wetness uom="">D</caaml:wetness><caaml:grainFormPrimary>RG</caaml:grainFormPrimary><caaml:grainFormSecondary>DF</caaml:grainFormSecondary><caaml:grainSize uom="mm"><caaml:Components><caaml:avg>0.25</caaml:avg><caaml:avgMax>0.75</caaml:avgMax></caaml:Components></caaml:grainSize><caaml:hardness uom="">F</caaml:hardness></caaml:Layer><caaml:Layer><caaml:depthTop uom="cm">3.0</caaml:depthTop><caaml:thickness uom="cm">8.0</caaml:thickness><caaml:wetness uom="">D</caaml:wetness><caaml:grainFormPrimary>FC</caaml:grainFormPrimary><caaml:grainFormSecondary>FCxr</caaml:grainFormSecondary><caaml:grainSize uom="mm"><caaml:Components><caaml:avg>0.5</caaml:avg><caaml:avgMax>1.0</caaml:avgMax></caaml:Components></caaml:grainSize><caaml:hardness uom="">F</caaml:hardness></caaml:Layer><caaml:Layer><caaml:depthTop uom="cm">11.0</caaml:depthTop><caaml:thickness uom="cm">1.0</caaml:thickness><caaml:wetness uom="">D</caaml:wetness><caaml:grainFormPrimary>FC</caaml:grainFormPrimary><caaml:grainFormSecondary>FCxr</caaml:grainFormSecondary><caaml:grainSize uom="mm"><caaml:Components><caaml:avg>0.5</caaml:avg><caaml:avgMax>0.75</caaml:avgMax></caaml:Components></caaml:grainSize><caaml:hardness uom="">4F-1F</caaml:hardness></caaml:Layer><caaml:Layer><caaml:depthTop uom="cm">12.0</caaml:depthTop><caaml:thickness uom="cm">9.0</caaml:thickness><caaml:wetness uom="">D</caaml:wetness><caaml:grainFormPrimary>FC</caaml:grainFormPrimary><caaml:grainFormSecondary>FCxr</caaml:grainFormSecondary><caaml:grainSize uom="mm"><caaml:Components><caaml:avg>1.0</caaml:avg><caaml:avgMax>1.75</caaml:avgMax></caaml:Components></caaml:grainSize><caaml:hardness uom="">F</caaml:hardness></caaml:Layer><caaml:Layer><caaml:depthTop uom="cm">21.0</caaml:depthTop><caaml:thickness uom="cm">17.0</caaml:thickness><caaml:wetness uom="">D</caaml:wetness><caaml:grainFormPrimary>FC</caaml:grainFormPrimary><caaml:grainFormSecondary>FCxr</caaml:grainFormSecondary><caaml:grainSize uom="mm"><caaml:Components><caaml:avg>0.5</caaml:avg><caaml:avgMax>1.25</caaml:avgMax></caaml:Components></caaml:grainSize><caaml:hardness uom="">1F</caaml:hardness></caaml:Layer><caaml:Layer><caaml:depthTop uom="cm">38.0</caaml:depthTop><caaml:thickness uom="cm">1.0</caaml:thickness><caaml:wetness uom="">D</caaml:wetness><caaml:grainFormPrimary>MF</caaml:grainFormPrimary><caaml:grainFormSecondary>FC</caaml:grainFormSecondary><caaml:grainSize uom="mm"><caaml:Components><caaml:avg>0.5</caaml:avg><caaml:avgMax>1.5</caaml:avgMax></caaml:Components></caaml:grainSize><caaml:hardness uom="">1F-P</caaml:hardness></caaml:Layer><caaml:Layer><caaml:depthTop uom="cm">39.0</caaml:depthTop><caaml:thickness uom="cm">10.0</caaml:thickness><caaml:wetness uom="">D</caaml:wetness><caaml:grainFormPrimary>FC</caaml:grainFormPrimary><caaml:grainFormSecondary>FCxr</caaml:grainFormSecondary><caaml:grainSize uom="mm"><caaml:Components><caaml:avg>1.0</caaml:avg><caaml:avgMax>1.25</caaml:avgMax></caaml:Components></caaml:grainSize><caaml:hardness uom="">1F</caaml:hardness></caaml:Layer><caaml:Layer><caaml:depthTop uom="cm">49.0</caaml:depthTop><caaml:thickness uom="cm">6.0</caaml:thickness><caaml:wetness uom="">D</caaml:wetness><caaml:grainFormPrimary>DH</caaml:grainFormPrimary><caaml:grainFormSecondary>FCxr</caaml:grainFormSecondary><caaml:grainSize uom="mm"><caaml:Components><caaml:avg>1.75</caaml:avg><caaml:avgMax>2.5</caaml:avgMax></caaml:Components></caaml:grainSize><caaml:hardness uom="">F</caaml:hardness></caaml:Layer><caaml:Layer><caaml:depthTop uom="cm">55.0</caaml:depthTop><caaml:thickness uom="cm">2.0</caaml:thickness><caaml:wetness uom="">D</caaml:wetness><caaml:grainFormPrimary>DH</caaml:grainFormPrimary><caaml:grainFormSecondary>FCxr</caaml:grainFormSecondary><caaml:grainSize uom="mm"><caaml:Components><caaml:avg>1.5</caaml:avg><caaml:avgMax>2.0</caaml:avgMax></caaml:Components></caaml:grainSize><caaml:hardness uom="">1F-P</caaml:hardness></caaml:Layer><caaml:Layer><caaml:depthTop uom="cm">57.0</caaml:depthTop><caaml:thickness uom="cm">4.0</caaml:thickness><caaml:wetness uom="">D</caaml:wetness><caaml:grainFormPrimary>DH</caaml:grainFormPrimary><caaml:grainFormSecondary>FCxr</caaml:grainFormSecondary><caaml:grainSize uom="mm"><caaml:Components><caaml:avg>2.0</caaml:avg><caaml:avgMax>3.0</caaml:avgMax></caaml:Components></caaml:grainSize><caaml:hardness uom="">F-4F</caaml:hardness></caaml:Layer><caaml:Layer><caaml:depthTop uom="cm">61.0</caaml:depthTop><caaml:thickness uom="cm">3.0</caaml:thickness><caaml:wetness uom="">D</caaml:wetness><caaml:grainFormPrimary>DH</caaml:grainFormPrimary><caaml:grainFormSecondary>FCxr</caaml:grainFormSecondary><caaml:grainSize uom="mm"><caaml:Components><caaml:avg>2.0</caaml:avg><caaml:avgMax>4.5</caaml:avgMax></caaml:Components></caaml:grainSize><caaml:hardness uom="">1F</caaml:hardness></caaml:Layer><caaml:Layer><caaml:depthTop uom="cm">64.0</caaml:depthTop><caaml:thickness uom="cm">12.0</caaml:thickness><caaml:wetness uom="">D</caaml:wetness><caaml:grainFormPrimary>DH</caaml:grainFormPrimary><caaml:grainSize uom="mm"><caaml:Components><caaml:avg>3.5</caaml:avg><caaml:avgMax>4.5</caaml:avgMax></caaml:Components></caaml:grainSize><caaml:hardness uom="">F</caaml:hardness></caaml:Layer></caaml:stratProfile><caaml:tempProfile><caaml:Obs><caaml:depth uom="cm">0.0</caaml:depth><caaml:snowTemp uom="degC">-3.4</caaml:snowTemp></caaml:Obs><caaml:Obs><caaml:depth uom="cm">6.0</caaml:depth><caaml:snowTemp uom="degC">-3.4</caaml:snowTemp></caaml:Obs><caaml:Obs><caaml:depth uom="cm">16.0</caaml:depth><caaml:snowTemp uom="degC">-3.7</caaml:snowTemp></caaml:Obs><caaml:Obs><caaml:depth uom="cm">26.0</caaml:depth><caaml:snowTemp uom="degC">-3.2</caaml:snowTemp></caaml:Obs><caaml:Obs><caaml:depth uom="cm">36.0</caaml:depth><caaml:snowTemp uom="degC">-2.6</caaml:snowTemp></caaml:Obs><caaml:Obs><caaml:depth uom="cm">46.0</caaml:depth><caaml:snowTemp uom="degC">-2.2</caaml:snowTemp></caaml:Obs><caaml:Obs><caaml:depth uom="cm">56.0</caaml:depth><caaml:snowTemp uom="degC">-1.7</caaml:snowTemp></caaml:Obs><caaml:Obs><caaml:depth uom="cm">66.0</caaml:depth><caaml:snowTemp uom="degC">-1.4</caaml:snowTemp></caaml:Obs><caaml:Obs><caaml:depth uom="cm">76.0</caaml:depth><caaml:snowTemp uom="degC">-1.0</caaml:snowTemp></caaml:Obs></caaml:tempProfile><caaml:densityProfile><caaml:Layer><caaml:depthTop uom="cm">0.0</caaml:depthTop><caaml:thickness uom="cm">4.0</caaml:thickness><caaml:density uom="kgm-3">184.0</caaml:density></caaml:Layer><caaml:Layer><caaml:depthTop uom="cm">4.0</caaml:depthTop><caaml:thickness uom="cm">4.0</caaml:thickness><caaml:density uom="kgm-3">212.0</caaml:density></caaml:Layer><caaml:Layer><caaml:depthTop uom="cm">8.0</caaml:depthTop><caaml:thickness uom="cm">4.0</caaml:thickness><caaml:density uom="kgm-3">248.0</caaml:density></caaml:Layer><caaml:Layer><caaml:depthTop uom="cm">12.0</caaml:depthTop><caaml:thickness uom="cm">4.0</caaml:thickness><caaml:density uom="kgm-3">299.0</caaml:density></caaml:Layer><caaml:Layer><caaml:depthTop uom="cm">16.0</caaml:depthTop><caaml:thickness uom="cm">4.0</caaml:thickness><caaml:density uom="kgm-3">239.0</caaml:density></caaml:Layer><caaml:Layer><caaml:depthTop uom="cm">20.0</caaml:depthTop><caaml:thickness uom="cm">4.0</caaml:thickness><caaml:density uom="kgm-3">288.0</caaml:density></caaml:Layer><caaml:Layer><caaml:depthTop uom="cm">24.0</caaml:depthTop><caaml:thickness uom="cm">4.0</caaml:thickness><caaml:density uom="kgm-3">362.0</caaml:density></caaml:Layer><caaml:Layer><caaml:depthTop uom="cm">28.0</caaml:depthTop><caaml:thickness uom="cm">4.0</caaml:thickness><caaml:density uom="kgm-3">355.0</caaml:density></caaml:Layer><caaml:Layer><caaml:depthTop uom="cm">32.0</caaml:depthTop><caaml:thickness uom="cm">4.0</caaml:thickness><caaml:density uom="kgm-3">356.0</caaml:density></caaml:Layer><caaml:Layer><caaml:depthTop uom="cm">36.0</caaml:depthTop><caaml:thickness uom="cm">4.0</caaml:thickness><caaml:density uom="kgm-3">359.0</caaml:density></caaml:Layer><caaml:Layer><caaml:depthTop uom="cm">40.0</caaml:depthTop><caaml:thickness uom="cm">4.0</caaml:thickness><caaml:density uom="kgm-3">360.0</caaml:density></caaml:Layer><caaml:Layer><caaml:depthTop uom="cm">44.0</caaml:depthTop><caaml:thickness uom="cm">4.0</caaml:thickness><caaml:density uom="kgm-3">352.0</caaml:density></caaml:Layer><caaml:Layer><caaml:depthTop uom="cm">48.0</caaml:depthTop><caaml:thickness uom="cm">4.0</caaml:thickness><caaml:density uom="kgm-3">242.0</caaml:density></caaml:Layer><caaml:Layer><caaml:depthTop uom="cm">52.0</caaml:depthTop><caaml:thickness uom="cm">4.0</caaml:thickness><caaml:density uom="kgm-3">283.0</caaml:density></caaml:Layer><caaml:Layer><caaml:depthTop uom="cm">56.0</caaml:depthTop><caaml:thickness uom="cm">4.0</caaml:thickness><caaml:density uom="kgm-3">200.0</caaml:density></caaml:Layer><caaml:Layer><caaml:depthTop uom="cm">60.0</caaml:depthTop><caaml:thickness uom="cm">4.0</caaml:thickness><caaml:density uom="kgm-3">191.0</caaml:density></caaml:Layer><caaml:Layer><caaml:depthTop uom="cm">64.0</caaml:depthTop><caaml:thickness uom="cm">4.0</caaml:thickness><caaml:density uom="kgm-3">214.0</caaml:density></caaml:Layer><caaml:Layer><caaml:depthTop uom="cm">68.0</caaml:depthTop><caaml:thickness uom="cm">8.0</caaml:thickness><caaml:density uom="kgm-3">199.0</caaml:density></caaml:Layer></caaml:densityProfile><caaml:hardnessProfile uomWeightHammer="kg" uomWeightTube="kg" uomDropHeight="cm"><caaml:hardnessMetaData><caaml:methodOfMeas>Ram Sonde</caaml:methodOfMeas></caaml:hardnessMetaData><caaml:Layer><caaml:depthTop uom="cm">0.0</caaml:depthTop><caaml:thickness uom="cm">8.0</caaml:thickness><caaml:hardness uom="N">9.81</caaml:hardness><caaml:weightHammer>0.0</caaml:weightHammer><caaml:weightTube>1.0</caaml:weightTube><caaml:nDrops>0.0</caaml:nDrops><caaml:dropHeight>0.0</caaml:dropHeight></caaml:Layer><caaml:Layer><caaml:depthTop uom="cm">8.0</caaml:depthTop><caaml:thickness uom="cm">4.0</caaml:thickness><caaml:hardness uom="N">19.62</caaml:hardness><caaml:weightHammer>1.0</caaml:weightHammer><caaml:weightTube>1.0</caaml:weightTube><caaml:nDrops>0.0</caaml:nDrops><caaml:dropHeight>0.0</caaml:dropHeight></caaml:Layer><caaml:Layer><caaml:depthTop uom="cm">12.0</caaml:depthTop><caaml:thickness uom="cm">2.0</caaml:thickness><caaml:hardness uom="N">44.145</caaml:hardness><caaml:weightHammer>1.0</caaml:weightHammer><caaml:weightTube>1.0</caaml:weightTube><caaml:nDrops>1.0</caaml:nDrops><caaml:dropHeight>5.0</caaml:dropHeight></caaml:Layer><caaml:Layer><caaml:depthTop uom="cm">14.0</caaml:depthTop><caaml:thickness uom="cm">9.0</caaml:thickness><caaml:hardness uom="N">25.07</caaml:hardness><caaml:weightHammer>1.0</caaml:weightHammer><caaml:weightTube>1.0</caaml:weightTube><caaml:nDrops>1.0</caaml:nDrops><caaml:dropHeight>5.0</caaml:dropHeight></caaml:Layer><caaml:Layer><caaml:depthTop uom="cm">23.0</caaml:depthTop><caaml:thickness uom="cm">6.0</caaml:thickness><caaml:hardness uom="N">142.245</caaml:hardness><caaml:weightHammer>1.0</caaml:weightHammer><caaml:weightTube>1.0</caaml:weightTube><caaml:nDrops>15.0</caaml:nDrops><caaml:dropHeight>5.0</caaml:dropHeight></caaml:Layer><caaml:Layer><caaml:depthTop uom="cm">29.0</caaml:depthTop><caaml:thickness uom="cm">7.0</caaml:thickness><caaml:hardness uom="N">159.76285714285714</caaml:hardness><caaml:weightHammer>1.0</caaml:weightHammer><caaml:weightTube>1.0</caaml:weightTube><caaml:nDrops>10.0</caaml:nDrops><caaml:dropHeight>10.0</caaml:dropHeight></caaml:Layer><caaml:Layer><caaml:depthTop uom="cm">36.0</caaml:depthTop><caaml:thickness uom="cm">5.0</caaml:thickness><caaml:hardness uom="N">215.82000000000002</caaml:hardness><caaml:weightHammer>1.0</caaml:weightHammer><caaml:weightTube>1.0</caaml:weightTube><caaml:nDrops>10.0</caaml:nDrops><caaml:dropHeight>10.0</caaml:dropHeight></caaml:Layer><caaml:Layer><caaml:depthTop uom="cm">41.0</caaml:depthTop><caaml:thickness uom="cm">7.0</caaml:thickness><caaml:hardness uom="N">229.8342857142857</caaml:hardness><caaml:weightHammer>1.0</caaml:weightHammer><caaml:weightTube>1.0</caaml:weightTube><caaml:nDrops>10.0</caaml:nDrops><caaml:dropHeight>15.0</caaml:dropHeight></caaml:Layer><caaml:Layer><caaml:depthTop uom="cm">48.0</caaml:depthTop><caaml:thickness uom="cm">8.0</caaml:thickness><caaml:hardness uom="N">56.407500000000006</caaml:hardness><caaml:weightHammer>1.0</caaml:weightHammer><caaml:weightTube>1.0</caaml:weightTube><caaml:nDrops>2.0</caaml:nDrops><caaml:dropHeight>15.0</caaml:dropHeight></caaml:Layer><caaml:Layer><caaml:depthTop uom="cm">56.0</caaml:depthTop><caaml:thickness uom="cm">2.0</caaml:thickness><caaml:hardness uom="N">93.19500000000001</caaml:hardness><caaml:weightHammer>1.0</caaml:weightHammer><caaml:weightTube>1.0</caaml:weightTube><caaml:nDrops>1.0</caaml:nDrops><caaml:dropHeight>15.0</caaml:dropHeight></caaml:Layer><caaml:Layer><caaml:depthTop uom="cm">58.0</caaml:depthTop><caaml:thickness uom="cm">6.0</caaml:thickness><caaml:hardness uom="N">35.970000000000006</caaml:hardness><caaml:weightHammer>1.0</caaml:weightHammer><caaml:weightTube>1.0</caaml:weightTube><caaml:nDrops>2.0</caaml:nDrops><caaml:dropHeight>5.0</caaml:dropHeight></caaml:Layer><caaml:Layer><caaml:depthTop uom="cm">64.0</caaml:depthTop><caaml:thickness uom="cm">12.0</caaml:thickness><caaml:hardness uom="N">23.707500000000003</caaml:hardness><caaml:weightHammer>1.0</caaml:weightHammer><caaml:weightTube>1.0</caaml:weightTube><caaml:nDrops>1.0</caaml:nDrops><caaml:dropHeight>5.0</caaml:dropHeight></caaml:Layer></caaml:hardnessProfile><caaml:stbTests><caaml:ExtColumnTest><caaml:noFailure/></caaml:ExtColumnTest><caaml:ExtColumnTest><caaml:failedOn><caaml:Layer><caaml:depthTop uom="cm">50.0</caaml:depthTop></caaml:Layer><caaml:Results><caaml:testScore>ECTP20</caaml:testScore></caaml:Results></caaml:failedOn></caaml:ExtColumnTest></caaml:stbTests></caaml:SnowProfileMeasurements></caaml:snowProfileResultsOf></caaml:SnowProfile>