<caaml:SnowProfile xmlns:caaml="http://caaml.org/Schemas/SnowProfileIACS/v6.0.3" xmlns:gml="http://www.opengis.net/gml" xmlns:slf="http://www.slf.ch/snowprofile/1.0" gml:id="e72534dc-521a-4bff-806b-cae58e0a0aac"><caaml:timeRef><caaml:recordTime><caaml:TimeInstant><caaml:timePosition>2009-04-30T12:30:00+02:00</caaml:timePosition></caaml:TimeInstant></caaml:recordTime><caaml:dateTimeReport>2009-04-30T23:08:25+02:00</caaml:dateTimeReport><caaml:dateTimeLastEdit>2009-05-08T13:35:47+02:00</caaml:dateTimeLastEdit></caaml:timeRef><caaml:srcRef/><caaml:locRef><caaml:name>Steint&#228;lli - Strela - Davos</caaml:name><caaml:validElevation><caaml:ElevationPosition uom="m"><caaml:position>2420</caaml:position></caaml:ElevationPosition></caaml:validElevation><caaml:validAspect><caaml:AspectPosition><caaml:position>E</caaml:position></caaml:AspectPosition></caaml:validAspect><caaml:validSlopeAngle><caaml:SlopeAnglePosition uom="deg"><caaml:position>25</caaml:position></caaml:SlopeAnglePosition></caaml:validSlopeAngle><caaml:pointLocation><gml:Point id="pointID" srsName="urn:ogc:def:crs:OGC:1.3:CRS84" srsDimension="2"><gml:pos>9.788804 46.807643</gml:pos></gml:Point></caaml:pointLocation></caaml:locRef><caaml:snowProfileResultsOf><caaml:SnowProfileMeasurements dir="top down"><caaml:profileDepth uom="cm">134.0</caaml:profileDepth><caaml:weatherCond><caaml:airTempPres uom="degC">-1.8</caaml:airTempPres></caaml:weatherCond><caaml:snowPackCond><caaml:hS><caaml:Components><caaml:height uom="cm">134.0</caaml:height></caaml:Components></caaml:hS></caaml:snowPackCond><caaml:stratProfile><caaml:Layer><caaml:depthTop uom="cm">0.0</caaml:depthTop><caaml:thickness uom="cm">12.0</caaml:thickness><caaml:wetness uom="">D-M</caaml:wetness><caaml:grainFormPrimary>PP</caaml:grainFormPrimary><caaml:grainFormSecondary>DF</caaml:grainFormSecondary><caaml:grainSize uom="mm"><caaml:Components><caaml:avg>1.0</caaml:avg><caaml:avgMax>1.5</caaml:avgMax></caaml:Components></caaml:grainSize><caaml:hardness uom="">F</caaml:hardness></caaml:Layer><caaml:Layer><caaml:depthTop uom="cm">12.0</caaml:depthTop><caaml:thickness uom="cm">4.0</caaml:thickness><caaml:wetness uom="">M</caaml:wetness><caaml:grainFormPrimary>RG</caaml:grainFormPrimary><caaml:grainFormSecondary>MF</caaml:grainFormSecondary><caaml:grainSize uom="mm"><caaml:Components><caaml:avg>0.75</caaml:avg><caaml:avgMax>1.0</caaml:avgMax></caaml:Components></caaml:grainSize><caaml:hardness uom="">1F</caaml:hardness></caaml:Layer><caaml:Layer><caaml:depthTop uom="cm">16.0</caaml:depthTop><caaml:thickness uom="cm">4.0</caaml:thickness><caaml:wetness uom="">D-M</caaml:wetness><caaml:grainFormPrimary>DF</caaml:grainFormPrimary><caaml:grainSize uom="mm"><caaml:Components><caaml:avg>0.75</caaml:avg><caaml:avgMax>1.0</caaml:avgMax></caaml:Components></caaml:grainSize><caaml:hardness uom="">F-4F</caaml:hardness></caaml:Layer><caaml:Layer><caaml:depthTop uom="cm">20.0</caaml:depthTop><caaml:thickness uom="cm">4.0</caaml:thickness><caaml:wetness uom="">M</caaml:wetness><caaml:grainFormPrimary>MFcr</caaml:grainFormPrimary><caaml:grainFormSecondary>MF</caaml:grainFormSecondary><caaml:grainSize uom="mm"><caaml:Components><caaml:avg>2.0</caaml:avg><caaml:avgMax>4.0</caaml:avgMax></caaml:Components></caaml:grainSize><caaml:hardness uom="">1F-P</caaml:hardness></caaml:Layer><caaml:Layer><caaml:depthTop uom="cm">24.0</caaml:depthTop><caaml:thickness uom="cm">1.0</caaml:thickness><caaml:wetness uom="">M-W</caaml:wetness><caaml:grainFormPrimary>MF</caaml:grainFormPrimary><caaml:grainSize uom="mm"><caaml:Components><caaml:avg>3.0</caaml:avg><caaml:avgMax>5.0</caaml:avgMax></caaml:Components></caaml:grainSize><caaml:hardness uom="">F</caaml:hardness></caaml:Layer><caaml:Layer><caaml:depthTop uom="cm">25.0</caaml:depthTop><caaml:thickness uom="cm">9.0</caaml:thickness><caaml:wetness uom="">M</caaml:wetness><caaml:grainFormPrimary>MFcr</caaml:grainFormPrimary><caaml:grainFormSecondary>MF</caaml:grainFormSecondary><caaml:grainSize uom="mm"><caaml:Components><caaml:avg>2.0</caaml:avg><caaml:avgMax>4.0</caaml:avgMax></caaml:Components></caaml:grainSize><caaml:hardness uom="">1F-P</caaml:hardness></caaml:Layer><caaml:Layer><caaml:depthTop uom="cm">34.0</caaml:depthTop><caaml:thickness uom="cm">17.0</caaml:thickness><caaml:wetness uom="">M-W</caaml:wetness><caaml:grainFormPrimary>MF</caaml:grainFormPrimary><caaml:grainSize uom="mm"><caaml:Components><caaml:avg>1.0</caaml:avg><caaml:avgMax>2.0</caaml:avgMax></caaml:Components></caaml:grainSize><caaml:hardness uom="">4F</caaml:hardness></caaml:Layer><caaml:Layer><caaml:depthTop uom="cm">51.0</caaml:depthTop><caaml:thickness uom="cm">34.0</caaml:thickness><caaml:wetness uom="">M</caaml:wetness><caaml:grainFormPrimary>MF</caaml:grainFormPrimary><caaml:grainSize uom="mm"><caaml:Components><caaml:avg>0.75</caaml:avg><caaml:avgMax>1.0</caaml:avgMax></caaml:Components></caaml:grainSize><caaml:hardness uom="">1F</caaml:hardness></caaml:Layer><caaml:Layer><caaml:depthTop uom="cm">85.0</caaml:depthTop><caaml:thickness uom="cm">40.0</caaml:thickness><caaml:wetness uom="">M</caaml:wetness><caaml:grainFormPrimary>MF</caaml:grainFormPrimary><caaml:grainSize uom="mm"><caaml:Components><caaml:avg>1.0</caaml:avg><caaml:avgMax>1.5</caaml:avgMax></caaml:Components></caaml:grainSize><caaml:hardness uom="">F-4F</caaml:hardness></caaml:Layer><caaml:Layer><caaml:depthTop uom="cm">125.0</caaml:depthTop><caaml:thickness uom="cm">9.0</caaml:thickness><caaml:wetness uom="">M</caaml:wetness><caaml:grainFormPrimary>MF</caaml:grainFormPrimary><caaml:grainFormSecondary>DH</caaml:grainFormSecondary><caaml:grainSize uom="mm"><caaml:Components><caaml:avg>2.0</caaml:avg><caaml:avgMax>3.0</caaml:avgMax></caaml:Components></caaml:grainSize><caaml:hardness uom="">F</caaml:hardness></caaml:Layer></caaml:stratProfile><caaml:tempProfile><caaml:Obs><caaml:depth uom="cm">0.0</caaml:depth><caaml:snowTemp uom="degC">-0.1</caaml:snowTemp></caaml:Obs><caaml:Obs><caaml:depth uom="cm">4.0</caaml:depth><caaml:snowTemp uom="degC">-0.2</caaml:snowTemp></caaml:Obs><caaml:Obs><caaml:depth uom="cm">9.0</caaml:depth><caaml:snowTemp uom="degC">-0.6</caaml:snowTemp></caaml:Obs><caaml:Obs><caaml:depth uom="cm">14.0</caaml:depth><caaml:snowTemp uom="degC">-0.1</caaml:snowTemp></caaml:Obs><caaml:Obs><caaml:depth uom="cm">19.0</caaml:depth><caaml:snowTemp uom="degC">-0.1</caaml:snowTemp></caaml:Obs><caaml:Obs><caaml:depth uom="cm">24.0</caaml:depth><caaml:snowTemp uom="degC">0.0</caaml:snowTemp></caaml:Obs><caaml:Obs><caaml:depth uom="cm">34.0</caaml:depth><caaml:snowTemp uom="degC">0.0</caaml:snowTemp></caaml:Obs><caaml:Obs><caaml:depth uom="cm">44.0</caaml:depth><caaml:snowTemp uom="degC">0.0</caaml:snowTemp></caaml:Obs><caaml:Obs><caaml:depth uom="cm">54.0</caaml:depth><caaml:snowTemp uom="degC">0.0</caaml:snowTemp></caaml:Obs><caaml:Obs><caaml:depth uom="cm">64.0</caaml:depth><caaml:snowTemp uom="degC">0.0</caaml:snowTemp></caaml:Obs><caaml:Obs><caaml:depth uom="cm">74.0</caaml:depth><caaml:snowTemp uom="degC">0.0</caaml:snowTemp></caaml:Obs><caaml:Obs><caaml:depth uom="cm">84.0</caaml:depth><caaml:snowTemp uom="degC">0.0</caaml:snowTemp></caaml:Obs><caaml:Obs><caaml:depth uom="cm">94.0</caaml:depth><caaml:snowTemp uom="degC">0.0</caaml:snowTemp></caaml:Obs><caaml:Obs><caaml:depth uom="cm">104.0</caaml:depth><caaml:snowTemp uom="degC">0.0</caaml:snowTemp></caaml:Obs><caaml:Obs><caaml:depth uom="cm">114.0</caaml:depth><caaml:snowTemp uom="degC">0.0</caaml:snowTemp></caaml:Obs><caaml:Obs><caaml:depth uom="cm">124.0</caaml:depth><caaml:snowTemp uom="degC">0.0</caaml:snowTemp></caaml:Obs><caaml:Obs><caaml:depth uom="cm">134.0</caaml:depth><caaml:snowTemp uom="degC">0.0</caaml:snowTemp></caaml:Obs></caaml:tempProfile><caaml:densityProfile><caaml:Layer><caaml:depthTop uom="cm">0.0</caaml:depthTop><caaml:thickness uom="cm">12.0</caaml:thickness><caaml:density uom="kgm-3">155.0</caaml:density></caaml:Layer><caaml:Layer><caaml:depthTop uom="cm">12.0</caaml:depthTop><caaml:thickness uom="cm">4.0</caaml:thickness><caaml:density uom="kgm-3">245.0</caaml:density></caaml:Layer><caaml:Layer><caaml:depthTop uom="cm">16.0</caaml:depthTop><caaml:thickness uom="cm">4.0</caaml:thickness><caaml:density uom="kgm-3">163.0</caaml:density></caaml:Layer><caaml:Layer><caaml:depthTop uom="cm">20.0</caaml:depthTop><caaml:thickness uom="cm">4.0</caaml:thickness><caaml:density uom="kgm-3">387.0</caaml:density></caaml:Layer><caaml:Layer><caaml:depthTop uom="cm">24.0</caaml:depthTop><caaml:thickness uom="cm">10.0</caaml:thickness><caaml:density uom="kgm-3">511.0</caaml:density></caaml:Layer><caaml:Layer><caaml:depthTop uom="cm">34.0</caaml:depthTop><caaml:thickness uom="cm">17.0</caaml:thickness><caaml:density uom="kgm-3">488.0</caaml:density></caaml:Layer><caaml:Layer><caaml:depthTop uom="cm">51.0</caaml:depthTop><caaml:thickness uom="cm">18.0</caaml:thickness><caaml:density uom="kgm-3">466.0</caaml:density></caaml:Layer><caaml:Layer><caaml:depthTop uom="cm">69.0</caaml:depthTop><caaml:thickness uom="cm">16.0</caaml:thickness><caaml:density uom="kgm-3">462.0</caaml:density></caaml:Layer><caaml:Layer><caaml:depthTop uom="cm">85.0</caaml:depthTop><caaml:thickness uom="cm">20.0</caaml:thickness><caaml:density uom="kgm-3">452.0</caaml:density></caaml:Layer><caaml:Layer><caaml:depthTop uom="cm">105.0</caaml:depthTop><caaml:thickness uom="cm">20.0</caaml:thickness><caaml:density uom="kgm-3">401.0</caaml:density></caaml:Layer><caaml:Layer><caaml:depthTop uom="cm">125.0</caaml:depthTop><caaml:thickness uom="cm">9.0</caaml:thickness><caaml:density uom="kgm-3">412.0</caaml:density></caaml:Layer></caaml:densityProfile><caaml:hardnessProfile uomWeightHammer="kg" uomWeightTube="kg" uomDropHeight="cm"><caaml:hardnessMetaData><caaml:methodOfMeas>Ram Sonde</caaml:methodOfMeas></caaml:hardnessMetaData><caaml:Layer><caaml:depthTop uom="cm">0.0</caaml:depthTop><caaml:thickness uom="cm">13.0</caaml:thickness><caaml:hardness uom="N">9.81</caaml:hardness><caaml:weightHammer>0.0</caaml:weightHammer><caaml:weightTube>1.0</caaml:weightTube><caaml:nDrops>0.0</caaml:nDrops><caaml:dropHeight>0.0</caaml:dropHeight></caaml:Layer><caaml:Layer><caaml:depthTop uom="cm">13.0</caaml:depthTop><caaml:thickness uom="cm">0.0</caaml:thickness><caaml:hardness uom="N">19.62</caaml:hardness><caaml:weightHammer>1.0</caaml:weightHammer><caaml:weightTube>1.0</caaml:weightTube><caaml:nDrops>0.0</caaml:nDrops><caaml:dropHeight>0.0</caaml:dropHeight></caaml:Layer><caaml:Layer><caaml:depthTop uom="cm">13.0</caaml:depthTop><caaml:thickness uom="cm">5.0</caaml:thickness><caaml:hardness uom="N">88.29</caaml:hardness><caaml:weightHammer>1.0</caaml:weightHammer><caaml:weightTube>1.0</caaml:weightTube><caaml:nDrops>7.0</caaml:nDrops><caaml:dropHeight>5.0</caaml:dropHeight></caaml:Layer><caaml:Layer><caaml:depthTop uom="cm">18.0</caaml:depthTop><caaml:thickness uom="cm">6.0</caaml:thickness><caaml:hardness uom="N">27.795</caaml:hardness><caaml:weightHammer>1.0</caaml:weightHammer><caaml:weightTube>1.0</caaml:weightTube><caaml:nDrops>1.0</caaml:nDrops><caaml:dropHeight>5.0</caaml:dropHeight></caaml:Layer><caaml:Layer><caaml:depthTop uom="cm">24.0</caaml:depthTop><caaml:thickness uom="cm">6.0</caaml:thickness><caaml:hardness uom="N">27.795</caaml:hardness><caaml:weightHammer>1.0</caaml:weightHammer><caaml:weightTube>1.0</caaml:weightTube><caaml:nDrops>1.0</caaml:nDrops><caaml:dropHeight>5.0</caaml:dropHeight></caaml:Layer><caaml:Layer><caaml:depthTop uom="cm">30.0</caaml:depthTop><caaml:thickness uom="cm">3.0</caaml:thickness><caaml:hardness uom="N">35.970000000000006</caaml:hardness><caaml:weightHammer>1.0</caaml:weightHammer><caaml:weightTube>1.0</caaml:weightTube><caaml:nDrops>1.0</caaml:nDrops><caaml:dropHeight>5.0</caaml:dropHeight></caaml:Layer><caaml:Layer><caaml:depthTop uom="cm">33.0</caaml:depthTop><caaml:thickness uom="cm">13.0</caaml:thickness><caaml:hardness uom="N">23.393076923076922</caaml:hardness><caaml:weightHammer>1.0</caaml:weightHammer><caaml:weightTube>1.0</caaml:weightTube><caaml:nDrops>1.0</caaml:nDrops><caaml:dropHeight>5.0</caaml:dropHeight></caaml:Layer><caaml:Layer><caaml:depthTop uom="cm">46.0</caaml:depthTop><caaml:thickness uom="cm">7.0</caaml:thickness><caaml:hardness uom="N">33.63428571428572</caaml:hardness><caaml:weightHammer>1.0</caaml:weightHammer><caaml:weightTube>1.0</caaml:weightTube><caaml:nDrops>2.0</caaml:nDrops><caaml:dropHeight>5.0</caaml:dropHeight></caaml:Layer><caaml:Layer><caaml:depthTop uom="cm">53.0</caaml:depthTop><caaml:thickness uom="cm">6.0</caaml:thickness><caaml:hardness uom="N">27.795</caaml:hardness><caaml:weightHammer>1.0</caaml:weightHammer><caaml:weightTube>1.0</caaml:weightTube><caaml:nDrops>1.0</caaml:nDrops><caaml:dropHeight>5.0</caaml:dropHeight></caaml:Layer><caaml:Layer><caaml:depthTop uom="cm">59.0</caaml:depthTop><caaml:thickness uom="cm">5.0</caaml:thickness><caaml:hardness uom="N">58.86</caaml:hardness><caaml:weightHammer>1.0</caaml:weightHammer><caaml:weightTube>1.0</caaml:weightTube><caaml:nDrops>4.0</caaml:nDrops><caaml:dropHeight>5.0</caaml:dropHeight></caaml:Layer><caaml:Layer><caaml:depthTop uom="cm">64.0</caaml:depthTop><caaml:thickness uom="cm">6.0</caaml:thickness><caaml:hardness uom="N">60.495000000000005</caaml:hardness><caaml:weightHammer>1.0</caaml:weightHammer><caaml:weightTube>1.0</caaml:weightTube><caaml:nDrops>5.0</caaml:nDrops><caaml:dropHeight>5.0</caaml:dropHeight></caaml:Layer><caaml:Layer><caaml:depthTop uom="cm">70.0</caaml:depthTop><caaml:thickness uom="cm">5.0</caaml:thickness><caaml:hardness uom="N">88.29</caaml:hardness><caaml:weightHammer>1.0</caaml:weightHammer><caaml:weightTube>1.0</caaml:weightTube><caaml:nDrops>7.0</caaml:nDrops><caaml:dropHeight>5.0</caaml:dropHeight></caaml:Layer><caaml:Layer><caaml:depthTop uom="cm">75.0</caaml:depthTop><caaml:thickness uom="cm">5.0</caaml:thickness><caaml:hardness uom="N">78.48</caaml:hardness><caaml:weightHammer>1.0</caaml:weightHammer><caaml:weightTube>1.0</caaml:weightTube><caaml:nDrops>6.0</caaml:nDrops><caaml:dropHeight>5.0</caaml:dropHeight></caaml:Layer><caaml:Layer><caaml:depthTop uom="cm">80.0</caaml:depthTop><caaml:thickness uom="cm">7.0</caaml:thickness><caaml:hardness uom="N">47.64857142857144</caaml:hardness><caaml:weightHammer>1.0</caaml:weightHammer><caaml:weightTube>1.0</caaml:weightTube><caaml:nDrops>4.0</caaml:nDrops><caaml:dropHeight>5.0</caaml:dropHeight></caaml:Layer><caaml:Layer><caaml:depthTop uom="cm">87.0</caaml:depthTop><caaml:thickness uom="cm">5.0</caaml:thickness><caaml:hardness uom="N">49.050000000000004</caaml:hardness><caaml:weightHammer>1.0</caaml:weightHammer><caaml:weightTube>1.0</caaml:weightTube><caaml:nDrops>3.0</caaml:nDrops><caaml:dropHeight>5.0</caaml:dropHeight></caaml:Layer><caaml:Layer><caaml:depthTop uom="cm">92.0</caaml:depthTop><caaml:thickness uom="cm">8.0</caaml:thickness><caaml:hardness uom="N">31.8825</caaml:hardness><caaml:weightHammer>1.0</caaml:weightHammer><caaml:weightTube>1.0</caaml:weightTube><caaml:nDrops>2.0</caaml:nDrops><caaml:dropHeight>5.0</caaml:dropHeight></caaml:Layer><caaml:Layer><caaml:depthTop uom="cm">100.0</caaml:depthTop><caaml:thickness uom="cm">4.0</caaml:thickness><caaml:hardness uom="N">44.145</caaml:hardness><caaml:weightHammer>1.0</caaml:weightHammer><caaml:weightTube>1.0</caaml:weightTube><caaml:nDrops>2.0</caaml:nDrops><caaml:dropHeight>5.0</caaml:dropHeight></caaml:Layer><caaml:Layer><caaml:depthTop uom="cm">104.0</caaml:depthTop><caaml:thickness uom="cm">6.0</caaml:thickness><caaml:hardness uom="N">27.795</caaml:hardness><caaml:weightHammer>1.0</caaml:weightHammer><caaml:weightTube>1.0</caaml:weightTube><caaml:nDrops>1.0</caaml:nDrops><caaml:dropHeight>5.0</caaml:dropHeight></caaml:Layer><caaml:Layer><caaml:depthTop uom="cm">110.0</caaml:depthTop><caaml:thickness uom="cm">20.0</caaml:thickness><caaml:hardness uom="N">22.0725</caaml:hardness><caaml:weightHammer>1.0</caaml:weightHammer><caaml:weightTube>1.0</caaml:weightTube><caaml:nDrops>1.0</caaml:nDrops><caaml:dropHeight>5.0</caaml:dropHeight></caaml:Layer><caaml:Layer><caaml:depthTop uom="cm">130.0</caaml:depthTop><caaml:thickness uom="cm">4.0</caaml:thickness><caaml:hardness uom="N">31.8825</caaml:hardness><caaml:weightHammer>1.0</caaml:weightHammer><caaml:weightTube>1.0</caaml:weightTube><caaml:nDrops>1.0</caaml:nDrops><caaml:dropHeight>5.0</caaml:dropHeight></caaml:Layer></caaml:hardnessProfile><caaml:stbTests><caaml:RBlockTest><caaml:failedOn><caaml:Layer><caaml:depthTop uom="cm">24.0</caaml:depthTop></caaml:Layer><caaml:Results><caaml:testScore>RB5</caaml:testScore><caaml:fractureCharacter>Irregular</caaml:fractureCharacter><caaml:releaseType>EB</caaml:releaseType></caaml:Results></caaml:failedOn></caaml:RBlockTest><caaml:ExtColumnTest><caaml:failedOn><caaml:Layer><caaml:depthTop uom="cm">34.0</caaml:depthTop></caaml:Layer><caaml:Results><caaml:testScore>ECTN19</caaml:testScore></caaml:Results></caaml:failedOn></caaml:ExtColumnTest></caaml:stbTests></caaml:SnowProfileMeasurements></caaml:snowProfileResultsOf></caaml:SnowProfile>